apiverve_worldnews/__init__.py
apiverve_worldnews/apiClient.py
apiverve_worldnews/exceptions.py
apiverve_worldnews/setup.py
apiverve_worldnews/setup_dep.py
apiverve_worldnews/tests/__init__.py
apiverve_worldnews/tests/test_api.py
apiverve_worldnews-1.1.5.dist-info/LICENSE
apiverve_worldnews-1.1.5.dist-info/METADATA
apiverve_worldnews-1.1.5.dist-info/WHEEL
apiverve_worldnews-1.1.5.dist-info/top_level.txt
apiverve_worldnews-1.1.5.dist-info/RECORD
